mssql_mcp_server/__init__.py
mssql_mcp_server/server.py
mssql_mcp_server_enhanced-1.0.0.dist-info/licenses/LICENSE
mssql_mcp_server_enhanced-1.0.0.dist-info/METADATA
mssql_mcp_server_enhanced-1.0.0.dist-info/WHEEL
mssql_mcp_server_enhanced-1.0.0.dist-info/entry_points.txt
mssql_mcp_server_enhanced-1.0.0.dist-info/top_level.txt
mssql_mcp_server_enhanced-1.0.0.dist-info/RECORD
